cursewords/__init__.py
cursewords/__main__.py
cursewords/characters.py
cursewords/chars.py
cursewords/cursewords.py
cursewords/printer.py
cursewords/puz.py
cursewords/version
cursewords-1.1.dist-info/LICENSE
cursewords-1.1.dist-info/METADATA
cursewords-1.1.dist-info/WHEEL
cursewords-1.1.dist-info/entry_points.txt
cursewords-1.1.dist-info/top_level.txt
cursewords-1.1.dist-info/RECORD
