Metadata-Version: 2.1
Name: cursewords
Version: 1.1
Summary: A terminal-based crossword puzzle solving interface
Home-page: https://github.com/thisisparker/cursewords
Author: Parker Higgins
Author-email: parker@parkerhiggins.net
License: UNKNOWN
Keywords: puz crossword crosswords xword xwords puzzle acrosslite
Platform: UNKNOWN
Classifier: Environment :: Console :: Curses
Classifier: License :: OSI Approved :: GNU Affero General Public License v3 or later (AGPLv3+)
Classifier: Programming Language :: Python :: 3
Classifier: Topic :: Games/Entertainment :: Puzzle Games
Requires-Python: >=3.4
License-File: LICENSE
Requires-Dist: blessed (==1.18.1)
